nfselib.issnet-0.2.0-py3.8-nspkg.pth
nfselib/issnet/__init__.py
nfselib/issnet/docs/conf.py
nfselib/issnet/docs/module_contents.txt
nfselib/issnet/v1_00/__init__.py
nfselib/issnet/v1_00/generatedsnamespaces.py
nfselib/issnet/v1_00/servico_cancelar_nfse_envio.py
nfselib/issnet/v1_00/servico_cancelar_nfse_resposta.py
nfselib/issnet/v1_00/servico_consultar_lote_rps_envio.py
nfselib/issnet/v1_00/servico_consultar_lote_rps_resposta.py
nfselib/issnet/v1_00/servico_consultar_nfse_resposta.py
nfselib/issnet/v1_00/servico_consultar_nfse_rps_envio.py
nfselib/issnet/v1_00/servico_consultar_situacao_lote_rps_envio.py
nfselib/issnet/v1_00/servico_consultar_situacao_lote_rps_resposta.py
nfselib/issnet/v1_00/servico_enviar_lote_rps_envio.py
nfselib/issnet/v1_00/servico_enviar_lote_rps_resposta.py
nfselib.issnet-0.2.0.dist-info/AUTHORS.rst
nfselib.issnet-0.2.0.dist-info/LICENSE
nfselib.issnet-0.2.0.dist-info/METADATA
nfselib.issnet-0.2.0.dist-info/WHEEL
nfselib.issnet-0.2.0.dist-info/namespace_packages.txt
nfselib.issnet-0.2.0.dist-info/top_level.txt
nfselib.issnet-0.2.0.dist-info/RECORD
