Metadata-Version: 2.1
Name: nfselib.issnet
Version: 0.2.0
Summary: Python Library to genereate issnet NFS-E
Home-page: https://github.com/erpbrasil/nfselib.issnet
Author: Luis Felipe Mileo
Author-email: mileo@kmee.com.br
License: MIT
Project-URL: Documentation, https://nfselibissnet.readthedocs.io/
Project-URL: Changelog, https://nfselibissnet.readthedocs.io/en/latest/changelog.html
Project-URL: Issue Tracker, https://github.com/erpbrasil/nfselib.issnet/issues
Platform: UNKNOWN
Classifier: Development Status :: 5 - Production/Stable
Classifier: Intended Audience :: Developers
Classifier: License :: OSI Approved :: MIT License
Classifier: Operating System :: Unix
Classifier: Operating System :: POSIX
Classifier: Operating System :: Microsoft :: Windows
Classifier: Programming Language :: Python
Classifier: Programming Language :: Python :: 3
Classifier: Programming Language :: Python :: 3.6
Classifier: Programming Language :: Python :: 3.7
Classifier: Programming Language :: Python :: 3.8
Classifier: Programming Language :: Python :: 3.9
Classifier: Programming Language :: Python :: Implementation :: CPython
Classifier: Programming Language :: Python :: Implementation :: PyPy
Classifier: Topic :: Utilities
Requires-Python: >=3.5, !=3.0.*, !=3.1.*, !=3.2.*, !=3.3.*, !=3.4.*
